pbdl/colors.py
pbdl/config.json
pbdl/dataset.py
pbdl/fetcher.py
pbdl/loader.py
pbdl/logging.py
pbdl/normalization.py
pbdl/utilities.py
pbdl/tools/preview.py
pbdl/torch/dataset.py
pbdl/torch/loader.py
pbdl/torch/phi/dataset.py
pbdl/torch/phi/loader.py
pbdl/torch/phi/sampler.py
pbdl-1.0.0.dist-info/licenses/LICENSE
pbdl-1.0.0.dist-info/METADATA
pbdl-1.0.0.dist-info/WHEEL
pbdl-1.0.0.dist-info/top_level.txt
pbdl-1.0.0.dist-info/RECORD
