Metadata-Version: 2.4
Name: pbdl
Version: 1.0.0
Summary: Manage datasets for physics-based deep learning
License:                                  Apache License
Project-URL: Homepage, https://github.com/tum-pbs/pbdl-dataset
Requires-Python: >=3.9
License-File: LICENSE
Requires-Dist: numpy>=1.0.0
Requires-Dist: h5py>=3.11.0
Requires-Dist: requests>=2.32.3
Provides-Extra: tools
Requires-Dist: opencv-python>=1.17.0; extra == "tools"
Provides-Extra: torch
Requires-Dist: torch>=2.0.0; extra == "torch"
Dynamic: license-file
